<?xml version="1.0" encoding="UTF-8"?>
<databaseChangeLog
        xmlns="http://www.liquibase.org/xml/ns/dbchangelog"
        xmlns:xsi="http://www.w3.org/2001/XMLSchema-instance"
        xsi:schemaLocation="http://www.liquibase.org/xml/ns/dbchangelog
        https://www.liquibase.org/xml/ns/dbchangelog/dbchangelog-4.25.xsd"
        logicalFilePath="db/changelog/003-create-tables.xml">

    <changeSet id="003-create-table" author="evgeniy_makeev">
        <createTable tableName="users" schemaName="non_public">
            <column name="login" type="VARCHAR(255)">
                <constraints primaryKey="true" nullable="false" unique="true"/>
            </column>
            <column name="password" type="VARCHAR(255)">
                <constraints nullable="false" />
            </column>
            <column name="admin" type="BOOLEAN" defaultValueBoolean="false">
                <constraints nullable="false"/>
            </column>
        </createTable>

        <createTable tableName="types_of_training" schemaName="non_public">
            <column name="id" type="BIGINT" defaultValueSequenceNext="types_of_training_id_seq">
                <constraints primaryKey="true" nullable="false"/>
            </column>

            <column name="type" type="VARCHAR(255)">
                <constraints nullable="false" unique="true"/>
            </column>
        </createTable>

        <createTable tableName="trainings" schemaName="non_public">
            <column name="id" type="BIGINT" defaultValueSequenceNext="trainings_id_seq">
                <constraints primaryKey="true" nullable="false"/>
            </column>

            <column name="user_login" type="VARCHAR(255)">
                <constraints foreignKeyName="trainings_user_login_users_login"
                             references="non_public.users(login)" referencedTableSchemaName="non_public"/>
            </column>

            <column name="type_of_training_id" type="BIGINT">
                <constraints foreignKeyName="indications_type_of_training_id_types_of_training_id"
                             references="non_public.types_of_training(id)" referencedTableSchemaName="non_public"/>
            </column>

            <column name="date" type="DATE">
                <constraints nullable="false"/>
            </column>

            <column name="duration" type="DOUBLE">
                <constraints nullable="false"/>
            </column>

            <column name="calories_burned" type="DOUBLE">
                <constraints nullable="false"/>
            </column>
        </createTable>

        <createTable tableName="additional_information" schemaName="non_public">
            <column name="training_id" type="BIGINT">
                <constraints foreignKeyName="additional_information_training_id_trainings_id"
                             references="non_public.trainings(id)" referencedTableSchemaName="non_public"/>
            </column>

            <column name="information" type="VARCHAR(255)">
                <constraints nullable="false"/>
            </column>

            <column name="value" type="DOUBLE">
                <constraints nullable="true"/>
            </column>
        </createTable>

        <createTable tableName="user_log_events" schemaName="non_public">
            <column name="date" type="DATE" defaultValueDate="CURRENT_DATE">
                <constraints nullable="false"/>
            </column>

            <column name="user_login" type="VARCHAR(255)">
                <constraints foreignKeyName="user_log_events_user_login_users_login"
                             references="non_public.users(login)" referencedTableSchemaName="non_public"/>
            </column>

            <column name="message" type="VARCHAR(255)">
                <constraints nullable="false"/>
            </column>
        </createTable>
    </changeSet>
</databaseChangeLog>
